aptisolve/__init__.py
aptisolve/__main__.py
aptisolve/cli.py
aptisolve/main.py
data_interpretation/__init__.py
data_interpretation/charts.py
data_interpretation/graphs.py
data_interpretation/tables.py
logical_reasoning/__init__.py
logical_reasoning/analogy.py
logical_reasoning/blood_relations.py
logical_reasoning/coding_decoding.py
logical_reasoning/direction_sense.py
logical_reasoning/number_series.py
logical_reasoning/puzzles.py
logical_reasoning/statement_conclusion.py
logical_reasoning/syllogisms.py
numerical_aptitude/__init__.py
numerical_aptitude/algebra.py
numerical_aptitude/averages.py
numerical_aptitude/compound_interest.py
numerical_aptitude/mixtures_alligations.py
numerical_aptitude/number_systems.py
numerical_aptitude/percentages.py
numerical_aptitude/permutations_combinations.py
numerical_aptitude/probability.py
numerical_aptitude/profit_loss.py
numerical_aptitude/ratios_proportions.py
numerical_aptitude/simple_interest.py
numerical_aptitude/time_speed_distance.py
numerical_aptitude/time_work.py
verbalapt/__init__.py
verbalapt/grammar_vocabulary.py
verbalapt/one_word_substitution.py
verbalapt/para_jumbles.py
verbalapt/reading_comprehension.py
verbalapt/sentence_completion.py
verbalapt/utils.py
verbalapt/data/antonyms.json
verbalapt/data/grammar_questions.json
verbalapt/data/para_jumbles.json
verbalapt/data/sentence_completion.json
verbalapt/data/synonyms.json
aptisolve-0.2.0.dist-info/METADATA
aptisolve-0.2.0.dist-info/WHEEL
aptisolve-0.2.0.dist-info/entry_points.txt
aptisolve-0.2.0.dist-info/top_level.txt
aptisolve-0.2.0.dist-info/RECORD
