Metadata-Version: 2.4
Name: aptisolve
Version: 0.2.0
Summary: A package for solving numerical and verbal aptitude problems
Home-page: https://github.com/yourusername/aptisolve
Author: Abishek, Nithish, Vishal, Praveen
Author-email: p26055114@gmail.com
Classifier: Programming Language :: Python :: 3
Classifier: License :: OSI Approved :: MIT License
Classifier: Operating System :: OS Independent
Classifier: Development Status :: 3 - Alpha
Classifier: Intended Audience :: Education
Classifier: Topic :: Education :: Computer Aided Instruction (CAI)
Requires-Python: >=3.6
Requires-Dist: click==8.1.8
Requires-Dist: python-dotenv==1.1.0
Dynamic: author
Dynamic: author-email
Dynamic: classifier
Dynamic: description
Dynamic: description-content-type
Dynamic: home-page
Dynamic: requires-dist
Dynamic: requires-python
Dynamic: summary
